var carolinaHall = {
"type": "FeatureCollection",
"crs": { "type": "name", "properties": { "name": "urn:ogc:def:crs:OGC:1.3:CRS84" } },
"features": [
{ "type": "Feature", "properties": { "id": 2, "descrip": "unc well" }, "geometry": { "type": "Point", "coordinates": [ -79.049807, 35.911271 ] } }
]
}
